credential/__init__.py
credential/admin.py
credential/apps.py
credential/forms.py
credential/models.py
credential/serializers.py
credential/tasks.py
credential/tests.py
credential/urls.py
credential/views.py
credential/form_builder/__init__.py
credential/form_builder/builder.py
credential/migrations/0001_initial.py
credential/migrations/0002_credential_subject_did.py
credential/migrations/0003_credentialblockchainregister.py
credential/migrations/0004_credentialblockchainregister_tx_hash.py
credential/migrations/__init__.py
credential/register_credentials_factory/__init__.py
credential/register_credentials_factory/abstractions.py
credential/register_credentials_factory/context.py
credential/register_credentials_factory/factory.py
credential/register_credentials_factory/models.py
credential/register_credentials_factory/strategy.py
credential/templates/render_form.html
credential/templates/admin/credential/change_form_credential.html
credential-0.0.2.dist-info/LICENSE
credential-0.0.2.dist-info/METADATA
credential-0.0.2.dist-info/WHEEL
credential-0.0.2.dist-info/top_level.txt
credential-0.0.2.dist-info/RECORD
