Metadata-Version: 2.1
Name: credential
Version: 0.0.2
Summary: A small credential handler app for django
Author-email: Alejandro <agarrido@izertis.com>
Classifier: Programming Language :: Python :: 3
Classifier: License :: OSI Approved :: MIT License
Classifier: Operating System :: OS Independent
Requires-Python: >=3.7
License-File: LICENSE
Requires-Dist: alastria-identity
Requires-Dist: Django (==4.1.3)
Requires-Dist: djangorestframework (==3.14.0)
Requires-Dist: drf-yasg (==1.21.4)
Requires-Dist: pillow (==9.3.0)
Requires-Dist: pyjwt (==2.6.0)
Requires-Dist: web3 (==5.31.3)
Requires-Dist: django-waffle (==3.0.0)
Requires-Dist: celery (==5.2.7)
Requires-Dist: django-jsonform (==2.15.0)
